rai_test/__init__.py
rai_test/demo.py
rai_test-1.0.5.dist-info/LICENSE
rai_test-1.0.5.dist-info/METADATA
rai_test-1.0.5.dist-info/WHEEL
rai_test-1.0.5.dist-info/top_level.txt
rai_test-1.0.5.dist-info/RECORD
