Metadata-Version: 2.1
Name: rai_test
Version: 1.0.5
Summary: Alibaba Cloud PAI-RAM SAM SDK Library for Python
License: Apache License 2.0
Requires-Python: >=3.6
License-File: LICENSE
